{
  "project_info": {
    "project_number": "807825082470",
    "project_id": "readerfortheblindv2",
    "storage_bucket": "readerfortheblindv2.appspot.com"
  },
  "client": [
    {
      "client_info": {
        "mobilesdk_app_id": "1:807825082470:android:0a5d3e37421fabc0b445a7",
        "android_client_info": {
          "package_name": "com.example.readerfortheblindv2"
        }
      },
      "oauth_client": [
        {
          "client_id": "807825082470-1icuvmubf50a2n287bddo5f2c3bq78ve.apps.googleusercontent.com",
          "client_type": 3
        }
      ],
      "api_key": [
        {
          "current_key": "AIzaSyDLXfBhWKwlD8HJe4zpLfCCmU8tmusiHiE"
        }
      ],
      "services": {
        "appinvite_service": {
          "other_platform_oauth_client": [
            {
              "client_id": "807825082470-1icuvmubf50a2n287bddo5f2c3bq78ve.apps.googleusercontent.com",
              "client_type": 3
            }
          ]
        }
      }
    }
  ],
  "configuration_version": "1"
}